Metadata-Version: 2.1
Name: python-dto
Version: 0.2.3
Summary: UNKNOWN
Home-page: https://github.com/Gaoshengyue/PyDto
Author: Symoon
Author-email: symoon.gao@gmail.com
License: MIT
Download-URL: https://github.com/Gaoshengyue/PyDto/releases/tag/0.2.3
Keywords: dto,DTO,Dto,PyDto,pydto,PyDto
Platform: UNKNOWN
Classifier: License :: OSI Approved :: MIT License
Classifier: Programming Language :: Python
Classifier: Intended Audience :: Developers
Classifier: Operating System :: OS Independent
